pipen_cli_init/__init__.py
pipen_cli_init/template/.copier-answers.yml.jinja
pipen_cli_init/template/README.md.jinja
pipen_cli_init/template/copier.yml
pipen_cli_init/template/pyproject.toml.jinja
pipen_cli_init/template/{{pipeline_name}}/__init__.py
pipen_cli_init/template/{{pipeline_name}}/__main__.py
pipen_cli_init/template/{{pipeline_name}}/main.py.jinja
pipen_cli_init/template/{{pipeline_name}}/processes.py.jinja
pipen_cli_init/template/{{pipeline_name}}/scripts/ExampleProcess.sh
pipen_cli_init/template/{{pipeline_name}}/{% if report %}reports{% endif %}/ExampleProcess.svelte
pipen_cli_init-1.1.0.dist-info/METADATA
pipen_cli_init-1.1.0.dist-info/WHEEL
pipen_cli_init-1.1.0.dist-info/entry_points.txt
pipen_cli_init-1.1.0.dist-info/RECORD
